kuest_eip712_structs/__init__.py
kuest_eip712_structs/domain_separator.py
kuest_eip712_structs/struct.py
kuest_eip712_structs/types.py
kuest_py_eip712_structs-0.0.2.dist-info/licenses/LICENSE
kuest_py_eip712_structs-0.0.2.dist-info/METADATA
kuest_py_eip712_structs-0.0.2.dist-info/WHEEL
kuest_py_eip712_structs-0.0.2.dist-info/top_level.txt
kuest_py_eip712_structs-0.0.2.dist-info/RECORD
