Metadata-Version: 2.4
Name: kuest-py-eip712-structs
Version: 0.0.2
Summary: A python library for EIP712 objects
Home-page: https://github.com/kuestcom/py-eip712-structs
Author: Kuest Engineering
Author-email: engineering@kuest.com
Maintainer: Kuest Engineering
Maintainer-email: engineering@kuest.com
Project-URL: Bug Tracker, https://github.com/kuestcom/py-eip712-structs
Classifier: Programming Language :: Python :: 3
Classifier: License :: OSI Approved :: MIT License
Classifier: Operating System :: OS Independent
Requires-Python: >=3.9.10
License-File: LICENSE
Requires-Dist: eth-utils>=4.1.1
Requires-Dist: pycryptodome>=3.20.0
Requires-Dist: pytest
Dynamic: author
Dynamic: author-email
Dynamic: classifier
Dynamic: description
Dynamic: description-content-type
Dynamic: home-page
Dynamic: license-file
Dynamic: maintainer
Dynamic: maintainer-email
Dynamic: project-url
Dynamic: requires-dist
Dynamic: requires-python
Dynamic: summary
